yodalib/__init__.py
yodalib/__main__.py
yodalib/plugin_installer.py
yodalib/api/__init__.py
yodalib/api/artifact_dict.py
yodalib/api/artifact_lifter.py
yodalib/api/decompiler_interface.py
yodalib/api/type_parser.py
yodalib/data/__init__.py
yodalib/data/state.py
yodalib/data/artifacts/__init__.py
yodalib/data/artifacts/artifact.py
yodalib/data/artifacts/comment.py
yodalib/data/artifacts/decompilation.py
yodalib/data/artifacts/enum.py
yodalib/data/artifacts/func.py
yodalib/data/artifacts/global_variable.py
yodalib/data/artifacts/patch.py
yodalib/data/artifacts/stack_variable.py
yodalib/data/artifacts/struct.py
yodalib/decompiler_stubs/__init__.py
yodalib/decompiler_stubs/ida_yodalib.py
yodalib/decompiler_stubs/angr_yodalib/__init__.py
yodalib/decompiler_stubs/binja_yodalib/__init__.py
yodalib/decompilers/__init__.py
yodalib/decompilers/angr/__init__.py
yodalib/decompilers/angr/artifact_lifter.py
yodalib/decompilers/angr/interface.py
yodalib/decompilers/angr/plugin.py
yodalib/decompilers/binja/__init__.py
yodalib/decompilers/binja/artifact_lifter.py
yodalib/decompilers/binja/interface.py
yodalib/decompilers/binja/plugin.py
yodalib/decompilers/ghidra/__init__.py
yodalib/decompilers/ghidra/artifact_lifter.py
yodalib/decompilers/ghidra/ghidra_api.py
yodalib/decompilers/ghidra/gui.py
yodalib/decompilers/ghidra/interface.py
yodalib/decompilers/ida/__init__.py
yodalib/decompilers/ida/artifact_lifter.py
yodalib/decompilers/ida/compat.py
yodalib/decompilers/ida/hooks.py
yodalib/decompilers/ida/interface.py
yodalib/decompilers/ida/plugin.py
yodalib/ui/__init__.py
yodalib/ui/qt_objects.py
yodalib/ui/utils.py
yodalib/ui/version.py
yodalib-0.2.0.dist-info/LICENSE
yodalib-0.2.0.dist-info/METADATA
yodalib-0.2.0.dist-info/WHEEL
yodalib-0.2.0.dist-info/entry_points.txt
yodalib-0.2.0.dist-info/top_level.txt
yodalib-0.2.0.dist-info/RECORD
