Metadata-Version: 2.1
Name: yodalib
Version: 0.2.0
Summary: Your Only Decompiler API Lib - A generic API to script in and out of decompilers
Home-page: https://github.com/binsync/yodalib
License: BSD 2 Clause
Classifier: License :: OSI Approved :: BSD License
Classifier: Programming Language :: Python :: 3
Classifier: Programming Language :: Python :: 3.6
Requires-Python: >=3.6
License-File: LICENSE
Requires-Dist: toml
Requires-Dist: pycparser
Requires-Dist: setuptools
Requires-Dist: prompt-toolkit
Requires-Dist: tqdm
Requires-Dist: ghidra-bridge
Requires-Dist: PySide6-Essentials >=6.4.2
Provides-Extra: test
Requires-Dist: angr-management ; extra == 'test'
Requires-Dist: pytest-qt ; extra == 'test'
